pyredai/__init__.py
pyredai/hello.py
pyredai-0.1.0.dist-info/LICENSE
pyredai-0.1.0.dist-info/METADATA
pyredai-0.1.0.dist-info/WHEEL
pyredai-0.1.0.dist-info/RECORD
