Metadata-Version: 2.1
Name: pyredai
Version: 0.1.0
Summary: PyRedAI is a python library to interact with LLMs using LangChain as a core of this library
Home-page: https://github.com/Redcomm-Shared-Dev/pyredai
License: Apache-2.0
Author: Cecep Aprilianto
Author-email: cecepaprilianto@gmail.com
Requires-Python: >=3.11,<4.0
Classifier: License :: OSI Approved :: Apache Software License
Classifier: Programming Language :: Python :: 3
Classifier: Programming Language :: Python :: 3.11
Project-URL: Repository, https://github.com/Redcomm-Shared-Dev/pyredai
